{
  "orchestrator": {
    "status": "idle",
    "current_cycle": 0,
    "current_agent": null,
    "start_time": null,
    "last_update": 1768359146.000268
  },
  "agents": {
    "frontend": {
      "status": "complete",
      "progress": 90,
      "message": "Frontend audit complete: 0 issues, 6 suggestions",
      "last_run": null,
      "last_result": null,
      "last_status_change": 1768359146.000268,
      "progress_history": [
        {
          "progress": 10,
          "timestamp": 1768359145.98437,
          "message": "Auditing frontend codebase..."
        },
        {
          "progress": 30,
          "timestamp": 1768359145.9890099,
          "message": "Checking for issues..."
        },
        {
          "progress": 50,
          "timestamp": 1768359145.9933062,
          "message": "Optimizing bundle..."
        },
        {
          "progress": 70,
          "timestamp": 1768359145.993715,
          "message": "Checking TypeScript..."
        },
        {
          "progress": 90,
          "timestamp": 1768359145.9981802,
          "message": "Analyzing improvements..."
        }
      ],
      "last_success": 1768359146.000268
    },
    "backend": {
      "status": "idle",
      "progress": 0,
      "message": "Ready",
      "last_run": null,
      "last_result": null
    },
    "api": {
      "status": "idle",
      "progress": 0,
      "message": "Ready",
      "last_run": null,
      "last_result": null
    },
    "styling": {
      "status": "idle",
      "progress": 0,
      "message": "Ready",
      "last_run": null,
      "last_result": null
    },
    "testing": {
      "status": "idle",
      "progress": 0,
      "message": "Ready",
      "last_run": null,
      "last_result": null
    },
    "security": {
      "status": "idle",
      "progress": 0,
      "message": "Ready",
      "last_run": null,
      "last_result": null
    },
    "documentation": {
      "status": "idle",
      "progress": 0,
      "message": "Ready",
      "last_run": null,
      "last_result": null
    },
    "deployment": {
      "status": "idle",
      "progress": 0,
      "message": "Ready",
      "last_run": null,
      "last_result": null
    }
  }
}