{
  "orchestrator": {
    "status": "idle",
    "current_cycle": 0,
    "current_agent": null,
    "start_time": null,
    "last_update": 1768354066.826014
  },
  "agents": {
    "frontend": {
      "status": "complete",
      "progress": 90,
      "message": "Frontend audit complete: 0 issues, 6 suggestions",
      "last_run": null,
      "last_result": null
    },
    "backend": {
      "status": "idle",
      "progress": 0,
      "message": "Ready",
      "last_run": null,
      "last_result": null
    },
    "api": {
      "status": "idle",
      "progress": 0,
      "message": "Ready",
      "last_run": null,
      "last_result": null
    },
    "styling": {
      "status": "idle",
      "progress": 0,
      "message": "Ready",
      "last_run": null,
      "last_result": null
    },
    "testing": {
      "status": "idle",
      "progress": 0,
      "message": "Ready",
      "last_run": null,
      "last_result": null
    },
    "security": {
      "status": "idle",
      "progress": 0,
      "message": "Ready",
      "last_run": null,
      "last_result": null
    },
    "documentation": {
      "status": "idle",
      "progress": 0,
      "message": "Ready",
      "last_run": null,
      "last_result": null
    },
    "deployment": {
      "status": "idle",
      "progress": 0,
      "message": "Ready",
      "last_run": null,
      "last_result": null
    }
  }
}